Linked_Lists/Linked_List.py
Linked_Lists/__init__.py
Linked_Lists-1.0.dist-info/LICENSE
Linked_Lists-1.0.dist-info/METADATA
Linked_Lists-1.0.dist-info/WHEEL
Linked_Lists-1.0.dist-info/top_level.txt
Linked_Lists-1.0.dist-info/RECORD
